coder_interpreter/__init__.py
coder_interpreter/server.py
coder_interpreter-0.1.6.dist-info/METADATA
coder_interpreter-0.1.6.dist-info/WHEEL
coder_interpreter-0.1.6.dist-info/entry_points.txt
coder_interpreter-0.1.6.dist-info/RECORD
