Metadata-Version: 2.4
Name: coder-interpreter
Version: 0.1.6
Summary: help users to do code execution. (with code execution, it helps users accomplish tasks in various work scenarios, such as document processing and analysis, etc.)
Author-email: yangming9042 <yangming9042@gmail.com>
Requires-Python: >=3.10
Requires-Dist: httpx>=0.28.0
Requires-Dist: mcp>=1.1.0
Requires-Dist: python-dotenv>=1.0.1
